dataloader/__init__.py
dataloader/ptb.py
dataloader/sequence.py
dataloader/spiral.py
layers/__init__.py
layers/basic.py
layers/recurrent.py
layers/seq2seq.py
deepnp-0.1.0.dist-info/LICENSE
deepnp-0.1.0.dist-info/METADATA
deepnp-0.1.0.dist-info/WHEEL
deepnp-0.1.0.dist-info/top_level.txt
deepnp-0.1.0.dist-info/RECORD
